browselite/__init__.py
browselite/app.py
browselite/config.py
browselite/core/__init__.py
browselite/core/autoclip.py
browselite/core/automation.py
browselite/core/autoweb.py
browselite/services/__init__.py
browselite/services/base.py
browselite/services/chatgpt.py
browselite/services/google.py
browselite/services/hugging_chat.py
browselite-0.0.2.dist-info/METADATA
browselite-0.0.2.dist-info/WHEEL
browselite-0.0.2.dist-info/RECORD
