Metadata-Version: 2.1
Name: browselite
Version: 0.0.2
Summary: automated browsing
Home-page: https://github.com/santhosh/
License: MIT
Author: Kammari Santhosh
Requires-Python: >=3.10,<4.0
Classifier: License :: OSI Approved :: MIT License
Classifier: Programming Language :: Python :: 3
Classifier: Programming Language :: Python :: 3.10
Classifier: Programming Language :: Python :: 3.11
Classifier: Programming Language :: Python :: 3.12
Classifier: Programming Language :: Python :: 3.13
Requires-Dist: loguru (>=0.7.3,<0.8.0)
Requires-Dist: pyautogui (>=0.9.52,<0.10.0)
Requires-Dist: pyperclip (>=1.9.0,<2.0.0)
Project-URL: Repository, https://github.com/santhosh/
